kvdl/__init__.py
kvdl/args.py
kvdl/certificate.py
kvdl/config.py
kvdl/hook.py
kvdl/keyvault.py
kvdl/main.py
kvdl/models.py
kvdl/output.py
kvdl-0.1.6.dist-info/LICENSE
kvdl-0.1.6.dist-info/METADATA
kvdl-0.1.6.dist-info/WHEEL
kvdl-0.1.6.dist-info/entry_points.txt
kvdl-0.1.6.dist-info/top_level.txt
kvdl-0.1.6.dist-info/RECORD
