Metadata-Version: 2.1
Name: kvdl
Version: 0.1.6
Summary: Download secrets from Keyvault
Home-page: https://github.com/travislikestocode/keyvault-cert-downloader
Author: Travis Brackett
Author-email: travmeister@gmail.com
License: UNKNOWN
Project-URL: Bug Tracker, https://github.com/travislikestocode/keyvault-cert-downloader/issues
Platform: UNKNOWN
Classifier: Programming Language :: Python :: 3
Classifier: License :: OSI Approved :: MIT License
Classifier: Operating System :: POSIX :: Linux
Requires-Python: >=3.6
License-File: LICENSE
Requires-Dist: pyyaml (>=5.4.1)
Requires-Dist: azure-identity (>=1.6.0)
Requires-Dist: azure-keyvault-secrets (>=4.3.0)
Requires-Dist: cryptography (>=3.4.7)
Requires-Dist: dbus-python (>=1.2.16)
Requires-Dist: xattr (>=0.9.7)
